odoo/addons/wms/__init__.py
odoo/addons/wms/__manifest__.py
odoo/addons/wms/i18n/it.po
odoo/addons/wms/i18n/wms.pot
odoo/addons/wms/models/__init__.py
odoo/addons/wms/models/res_config_settings.py
odoo/addons/wms/security/wms_security.xml
odoo/addons/wms/static/description/icon.png
odoo/addons/wms/views/res_config_settings_views.xml
odoo/addons/wms/views/wms_views.xml
odoo12_addon_wms-12.0.1.0.0.99.dev10.dist-info/METADATA
odoo12_addon_wms-12.0.1.0.0.99.dev10.dist-info/WHEEL
odoo12_addon_wms-12.0.1.0.0.99.dev10.dist-info/top_level.txt
odoo12_addon_wms-12.0.1.0.0.99.dev10.dist-info/RECORD
